autogovernance/__init__.py
autogovernance/browser.py
autogovernance/core.py
autogovernance/element.py
autogovernance/main.py
autogovernance/tables.py
Autogovernance-0.8.0.dist-info/LICENSE
Autogovernance-0.8.0.dist-info/METADATA
Autogovernance-0.8.0.dist-info/WHEEL
Autogovernance-0.8.0.dist-info/top_level.txt
Autogovernance-0.8.0.dist-info/RECORD
