Metadata-Version: 2.1
Name: Autogovernance
Version: 0.8.0
Summary: Package to update information in Governance
Home-page: https://github.com/JulioPestanaSalinas/AutoGovernance
Author: Julio Pestaña Salinas
Author-email: Julio.Pestana.Salinas@es.ey.com
License: GNU
Platform: UNKNOWN
Requires-Python: >=3.6
